koob_resume/__init__.py
koob_resume/__main__.py
koob_resume/koob_resume.py
koob_resume/resume.py
koob_resume-0.1.3.dist-info/licenses/LICENSE
koob_resume-0.1.3.dist-info/METADATA
koob_resume-0.1.3.dist-info/WHEEL
koob_resume-0.1.3.dist-info/entry_points.txt
koob_resume-0.1.3.dist-info/top_level.txt
koob_resume-0.1.3.dist-info/RECORD
