Metadata-Version: 2.4
Name: koob_resume
Version: 0.1.3
Summary: A Python application to create a pdf resume.
Author-email: Philip Brown <philip@koob.foo>
Maintainer-email: Philip Brown <philip@koob.foo>
License: MIT AND (Apache-2.0 OR BSD-2-Clause)
Project-URL: Homepage, https://github.com/koobfoo/koob-resume
Project-URL: Repository, https://github.com/koobfoo/koob-resume
Keywords: koob,python,resume,pdf
Classifier: Programming Language :: Python :: 3
Classifier: Programming Language :: Python :: 3.8
Classifier: Programming Language :: Python :: 3.9
Classifier: Programming Language :: Python :: 3.10
Classifier: Programming Language :: Python :: 3.11
Classifier: Operating System :: OS Independent
Requires-Python: >=3.8
License-File: LICENSE
Requires-Dist: fpdf2
Provides-Extra: dev
Requires-Dist: pre-commit; extra == "dev"
Requires-Dist: ruff; extra == "dev"
Requires-Dist: pytest; extra == "dev"
Requires-Dist: pip-audit; extra == "dev"
Requires-Dist: pip>=25.3; extra == "dev"
Requires-Dist: setuptools>=80.9.0; extra == "dev"
Dynamic: license-file
